push_to_gdoc/__init__.py
push_to_gdoc/document.py
push_to_gdoc/google_api_services.py
push_to_gdoc-0.1.0.dist-info/LICENSE
push_to_gdoc-0.1.0.dist-info/METADATA
push_to_gdoc-0.1.0.dist-info/WHEEL
push_to_gdoc-0.1.0.dist-info/top_level.txt
push_to_gdoc-0.1.0.dist-info/RECORD
