Metadata-Version: 2.1
Name: push-to-gdoc
Version: 0.1.0
Summary: Get data from python into Google Docs
Home-page: https://github.com/OpenDataServices/push_to_gdoc/
Author: David Raznick
Author-email: david.raznick@opendataservices.coop
License: The MIT License (MIT)
Requires-Dist: matplotlib
Requires-Dist: pandas
Requires-Dist: appdirs
Requires-Dist: google-api-python-client
Requires-Dist: google-auth-oauthlib
Requires-Dist: google
Provides-Extra: test
Requires-Dist: pytest ; extra == 'test'
Requires-Dist: black ; extra == 'test'
